{
  "Tabs": {
    "Info": "ข้อมูล",
    "Main": "หลัก",
    "ESP": "ESP"
  },
  
  "Sections": {
    "info": ["ข้อมูล", "ข้อมูลของบัญชีและผู้เล่น"],
    "Update": ["อัปเดต", "บันทึกการอัปเดตล่าสุด"],
    "future update": ["การอัปเดตในอนาคต", "แผนการอัปเดตที่จะมาถึง"],
    "Main": ["หลัก", "ฟีเจอร์หลักของสคริปต์"],
    "esp": ["ESP", "ฟีเจอร์สำหรับเน้นผู้เล่นและวัตถุ"]
  },
  
  "Labels": {
    "Welcome": ["ยินดีต้อนรับ", "ชื่อสวย!"],
    "Account Age": ["อายุบัญชี", "จำนวนวันของบัญชี"],
    "Added: Button | finish generator": ["เพิ่ม: ปุ่ม | เสร็จสิ้นเครื่องกำเนิด", "ทำเครื่องกำเนิดให้เสร็จ"],
    "Toggle: Auto Generator": ["สลับ: เครื่องกำเนิดอัตโนมัติ", "เดินไปที่เครื่องกำเนิดและทำให้เสร็จ อย่าขยับ!"],
    "Working?": ["กำลังทำงาน?", "ใช่ / อัปเดตวันนี้"],
    "Update day": ["วันที่อัปเดต", "ไม่มีวันที่กำหนด"],
    "Finish generator | Button": ["เสร็จสิ้นเครื่องกำเนิด | ปุ่ม", "สแปม = เตะหรือแบน"]
  },
  
  "Buttons": {
    "finish generator": ["เสร็จสิ้นเครื่องกำเนิด", "สั่งให้เครื่องกำเนิดเสร็จทันที"]
  },
  
  "Toggles": {
    "Generator (s)": ["เครื่องกำเนิด (s)", "เน้นเครื่องกำเนิดไฟฟ้า"],
    "Survivor (s)": ["ผู้รอดชีวิต (s)", "เน้นผู้รอดชีวิต"],
    "Killer (s)": ["ฆาตกร (s)", "เน้นฆาตกร"]
  },
  
  "Account Messages": {
    "5 years": "บัญชี 5 ปี... ยินดีด้วยนักรบ :D",
    "4 years": "บัญชี 4 ปี... ยินดีด้วย :D",
    "3 years": "บัญชี 3 ปี... ยินดีด้วย :D",
    "2 years": "บัญชี 2 ปี... ยินดีด้วย :D",
    "1 year": "บัญชี 1 ปี... ยินดีด้วย :D",
    "almost 1 year": "เกือบ 1 ปีแล้ว สู้ต่อไป! :D",
    "still new": "ยังใหม่อยู่ :D",
    "just started": "เพิ่งเริ่ม?"
  }
}
